[{"project": "company", "path": "tests/cognition_info_acceptance.py", "root": "/home/tim/company"}, {"project": "company", "path": "tests/cognition_info_registries_acceptance.py", "root": "/home/tim/company"}, {"project": "company", "path": "tests/cognition_resolution_loop_acceptance.py", "root": "/home/tim/company"}, {"project": "company", "path": "tests/coherence_cli_acceptance.py", "root": "/home/tim/company"}, {"project": "company", "path": "tests/commit_queue_acceptance.py", "root": "/home/tim/company"}, {"project": "company", "path": "tests/compose_acceptance.py", "root": "/home/tim/company"}]