{"project": "company", "path": "store/.gitkeep", "model": "kimi-k2.7-code:cloud", "prompt_version": "v2-full", "what_it_does": "An empty Git placeholder file that ensures the store/ directory is tracked by version control even when it contains no other files.", "observations": ["File is completely empty", "Filename is .gitkeep", "Located in the company/store/ directory"], "standouts": [], "conventions": ["Follows the common Git convention of using a .gitkeep file to preserve an otherwise empty directory in a repository"], "concerns": [], "notes": "Empty .gitkeep placeholder that keeps the store directory under version control.", "questions": [], "purpose_vs_actual": "The stated purpose of tracking an empty directory matches the actual empty .gitkeep file.", "apparent_themes": ["version control housekeeping", "directory scaffolding", "repository structure preservation"], "intention_signals": "Preserve the store/ directory in the repository so it remains available for runtime, build, or deployment use even when empty.", "novelty": "n/a", "contribution": "Ensures the store/ directory is not pruned by Git, providing a stable filesystem path for downstream processes.", "summary_for_embedding": "The file company/store/.gitkeep is an empty Git placeholder that keeps the store directory tracked in version control.", "intention_for_embedding": "Ensure the store directory is retained in the repository even when it has no other contents.", "suggested_fields": [], "proposed_edge_kinds": [], "symbols": []}